{"results":[{"id":592479,"title":"Kale and Quinoa Salad with Black Beans","readyInMinutes":50,"servings":6,"image":"Kale-and-Quinoa-Salad-with-Black-Beans-592479.jpg","imageUrls":["Kale-and-Quinoa-Salad-with-Black-Beans-592479.jpg"]},{"id":547775,"title":"Creamy Avocado Pasta","readyInMinutes":15,"servings":2,"image":"Creamy-Avocado-Pasta-547775.jpg","imageUrls":["Creamy-Avocado-Pasta-547775.jpg"]},{"id":818941,"title":"Avocado Toast with Eggs, Spinach, and Tomatoes","readyInMinutes":10,"servings":1,"image":"avocado-toast-with-eggs-spinach-and-tomatoes-818941.jpg","imageUrls":["avocado-toast-with-eggs-spinach-and-tomatoes-818941.jpg"]},{"id":495111,"title":"Citrus Sesame Kale","readyInMinutes":15,"servings":4,"image":"Citrus-Sesame-Kale-495111.jpg","imageUrls":["Citrus-Sesame-Kale-495111.jpg"]},{"id":689502,"title":"Melt In Your Mouth Kale Salad","readyInMinutes":10,"servings":2,"image":"Melt-In-Your-Mouth-Kale-Salad-689502.jpg","imageUrls":["Melt-In-Your-Mouth-Kale-Salad-689502.jpg"]}],"baseUri":"https://spoonacular.com/recipeImages/","offset":0,"number":5,"totalResults":314558,"processingTimeMs":773,"expires":1583726576679,"isStale":false}